king_tools/__init__.py
king_tools/data_file_tool.py
king_tools/media_encoder_tool.py
king_tool-0.1.2.dist-info/METADATA
king_tool-0.1.2.dist-info/WHEEL
king_tool-0.1.2.dist-info/top_level.txt
king_tool-0.1.2.dist-info/RECORD
